README.md
setup.cfg
setup.py
bin/json-delete
bin/json-dump
bin/json-get
bin/json-grep
bin/json-post
bin/json-put
bin/json-validate
jsontester/__init__.py
jsontester/apitester.py
jsontester/cookies.py
jsontester/log.py
jsontester/request.py
jsontester/responsecodes.py
jsontester/shell.py
jsontester/sqlite.py
jsontester.egg-info/PKG-INFO
jsontester.egg-info/SOURCES.txt
jsontester.egg-info/dependency_links.txt
jsontester.egg-info/requires.txt
jsontester.egg-info/top_level.txt
test/__init__.py
test/test_responsecodes.py