Metadata-Version: 1.0
Name: jsontester
Version: 1.1.3
Summary: Scripts to test JSON API requests from command line
Home-page: https://github.com/hile/jsontester
Author: Ilkka Tuohela
Author-email: hile@iki.fi
License: PSF
Keywords: json request test browser
Platform: UNKNOWN
